PyMMM.cpython-312-x86_64-linux-gnu.so
include/pybind11_json/pybind11_json.hpp
pymmm-0.7.11.dist-info/METADATA
pymmm-0.7.11.dist-info/WHEEL
pymmm-0.7.11.dist-info/RECORD
share/pkgconfig/pybind11_json.pc
share/cmake/pybind11_json/pybind11_jsonConfig.cmake
share/cmake/pybind11_json/pybind11_jsonTargets.cmake
share/cmake/pybind11_json/pybind11_jsonConfigVersion.cmake
